rdkit-stubs/install/__main__.py
rdkit-stubs/install/align.py
rdkit-stubs/install/classes.py
rdkit-stubs/install/combine.py
rdkit-stubs/install/download.py
rdkit-stubs/install/find.py
rdkit-stubs/install/infer.py
rdkit-stubs/install/modules.py
rdkit-stubs/install/monkey_ast.py
rdkit-stubs/install/parse.py
rdkit-stubs/install/unparse.py
rdkit-stubs/install/utils.py
rdkit_doc_stubs-0.0.2.dist-info/METADATA
rdkit_doc_stubs-0.0.2.dist-info/WHEEL
rdkit_doc_stubs-0.0.2.dist-info/top_level.txt
rdkit_doc_stubs-0.0.2.dist-info/RECORD
