Metadata-Version: 2.1
Name: rdkit-doc-stubs
Version: 0.0.2
Summary: Combined stubs from RDKit's documentation and mypy's stubgen
Author: Tim Hörmann
Author-email: t.hoermann@audivir.de
Project-URL: homepage, https://www.audivir.de/
Project-URL: repository, https://github.com/tim25651/rdkit-doc-stubs
Requires-Python: >=3.10
Requires-Dist: rdkit (==2023.3.1)
Requires-Dist: mypy
Requires-Dist: isort
Requires-Dist: black
Requires-Dist: biopython
